rustic_ai/litellm/__init__.py
rustic_ai/litellm/agent.py
rustic_ai/litellm/agent_ext/__init__.py
rustic_ai/litellm/agent_ext/llm.py
rustic_ai/litellm/conf.py
rustic_ai/litellm/utils.py
rustic_ai/litellm/xform_helpers.py
rusticai_litellm-1.0.0.dist-info/METADATA
rusticai_litellm-1.0.0.dist-info/WHEEL
rusticai_litellm-1.0.0.dist-info/RECORD
