Metadata-Version: 2.4
Name: rusticai-litellm
Version: 1.0.0
Summary: Rustic AI module leveraging LiteLLM for LLMs
License-Expression: Apache-2.0
Author: Dragonscale Industries Inc.
Author-email: dev@dragonscale.ai
Requires-Python: >=3.12,<3.13
Classifier: Programming Language :: Python :: 3
Classifier: Programming Language :: Python :: 3.12
Provides-Extra: test
Requires-Dist: dotenv (>=0.9.9,<0.10.0)
Requires-Dist: fastapi-sso (>=0.18.0,<0.19.0)
Requires-Dist: litellm (>=1.75.0,<2.0.0)
Requires-Dist: openai (>=1.71.0,<2.0.0)
Requires-Dist: rusticai-core (>=1.0.0,<1.1.0)
Project-URL: Homepage, https://www.rustic.ai/
Project-URL: Repository, https://github.com/rustic-ai/rustic-ai
Project-URL: Rustic AI Core, https://pypi.org/project/rusticai-core/
